onepkg/__init__.py
onepkg/cli.py
onepkg/managers.py
onepkg/manifest.py
onepkg/models.py
onepkg/specs.yaml
onepkg/utils.py
onepkg-0.6.0.dist-info/METADATA
onepkg-0.6.0.dist-info/WHEEL
onepkg-0.6.0.dist-info/entry_points.txt
onepkg-0.6.0.dist-info/top_level.txt
onepkg-0.6.0.dist-info/RECORD
