Metadata-Version: 2.4
Name: onepkg
Version: 0.6.0
Summary: One manager to manage them all - unified CLI for brew, cargo, uv, go, and more
Requires-Python: >=3.10
Requires-Dist: PyYAML>=6
Requires-Dist: cyclopts>=3.20.0
Requires-Dist: rich>=13.0.0
Provides-Extra: dev
Requires-Dist: pytest>=8.0; extra == "dev"
Requires-Dist: pytest-cov>=4.0; extra == "dev"
Requires-Dist: ruff>=0.8.0; extra == "dev"
